LICENSE
README.md
setup.py
CyberBook/__init__.py
CyberBook.egg-info/PKG-INFO
CyberBook.egg-info/SOURCES.txt
CyberBook.egg-info/dependency_links.txt
CyberBook.egg-info/not-zip-safe
CyberBook.egg-info/requires.txt
CyberBook.egg-info/top_level.txt
CyberBook/Background/__init__.py
CyberBook/Background/http_server.py
CyberBook/Background/socket_server.py
CyberBook/DecoderRing/__init__.py
CyberBook/DecoderRing/main.py
CyberBook/DecoderRing/utils.py
CyberBook/Identify/__init__.py
CyberBook/Identify/os_specifics.py
CyberBook/Lists/__init__.py
CyberBook/Lists/traversal_list.py
CyberBook/Lists/utils.py
CyberBook/Misc/__init__.py
CyberBook/Misc/reverse_shell.py
CyberBook/Misc/tools.py