Metadata-Version: 2.1
Name: CyberBook
Version: 0.0.26
Summary: Cyber spellbook for developers.
Author: Clutch_Reboot
Author-email: clutchshadow26@gmail.com
License: GNU General Public License v3.0
Project-URL: Documentation, https://clutchreboot.github.io/CyberBookDocs/
Project-URL: Source, https://github.com/ClutchReboot/CyberBook
Keywords: cyberbook DecoderRing tools
Requires-Python: >=3.10
License-File: LICENSE
